drdictaphone_neovim/DrDictaphone.py
drdictaphone_neovim_plugin-0.9.1.dist-info/LICENSE
drdictaphone_neovim_plugin-0.9.1.dist-info/METADATA
drdictaphone_neovim_plugin-0.9.1.dist-info/WHEEL
drdictaphone_neovim_plugin-0.9.1.dist-info/top_level.txt
drdictaphone_neovim_plugin-0.9.1.dist-info/RECORD
