Metadata-Version: 2.1
Name: drdictaphone-neovim-plugin
Version: 0.9.1
Summary: DrDictaphone plugin for Neovim
Author-email: Ole Kliemann <mail@olekliemann.de>
License: 
Project-URL: homepage, https://github.com/olekli/DrDictaphone
Classifier: Programming Language :: Python :: 3
Classifier: License :: OSI Approved :: Apache Software License
Classifier: Operating System :: OS Independent
Classifier: Development Status :: 4 - Beta
Classifier: Topic :: Text Processing
Classifier: Intended Audience :: Developers
Classifier: Intended Audience :: End Users/Desktop
Requires-Python: >=3.6
License-File: LICENSE
Requires-Dist: MrEventLoop >=0.6.2
Requires-Dist: drdictaphone-shared >=0.9.1
Requires-Dist: pynvim >=0.5.0
